<tbody>
 <row>
  <entry>B011</entry>
  <entry></entry>
  <entry>Embedded Ada</entry>
  <entry></entry>
 </row>
 <row>
  <entry>B013</entry>
  <entry></entry>
  <entry>Embedded COBOL</entry>
  <entry></entry>
 </row>
 <row>
  <entry>B014</entry>
  <entry></entry>
  <entry>Embedded Fortran</entry>
  <entry></entry>
 </row>
 <row>
  <entry>B015</entry>
  <entry></entry>
  <entry>Embedded MUMPS</entry>
  <entry></entry>
 </row>
 <row>
  <entry>B016</entry>
  <entry></entry>
  <entry>Embedded Pascal</entry>
  <entry></entry>
 </row>
 <row>
  <entry>B017</entry>
  <entry></entry>
  <entry>Embedded PL/I</entry>
  <entry></entry>
 </row>
 <row>
  <entry>B031</entry>
  <entry></entry>
  <entry>Basic dynamic SQL</entry>
  <entry></entry>
 </row>
 <row>
  <entry>B032</entry>
  <entry></entry>
  <entry>Extended dynamic SQL</entry>
  <entry></entry>
 </row>
 <row>
  <entry>B032-01</entry>
  <entry></entry>
  <entry>&lt;describe input statement&gt;</entry>
  <entry></entry>
 </row>
 <row>
  <entry>B033</entry>
  <entry></entry>
  <entry>Untyped SQL-invoked function arguments</entry>
  <entry></entry>
 </row>
 <row>
  <entry>B034</entry>
  <entry></entry>
  <entry>Dynamic specification of cursor attributes</entry>
  <entry></entry>
 </row>
 <row>
  <entry>B041</entry>
  <entry></entry>
  <entry>Extensions to embedded SQL exception declarations</entry>
  <entry></entry>
 </row>
 <row>
  <entry>B051</entry>
  <entry></entry>
  <entry>Enhanced execution rights</entry>
  <entry></entry>
 </row>
 <row>
  <entry>B111</entry>
  <entry></entry>
  <entry>Module language Ada</entry>
  <entry></entry>
 </row>
 <row>
  <entry>B112</entry>
  <entry></entry>
  <entry>Module language C</entry>
  <entry></entry>
 </row>
 <row>
  <entry>B113</entry>
  <entry></entry>
  <entry>Module language COBOL</entry>
  <entry></entry>
 </row>
 <row>
  <entry>B114</entry>
  <entry></entry>
  <entry>Module language Fortran</entry>
  <entry></entry>
 </row>
 <row>
  <entry>B115</entry>
  <entry></entry>
  <entry>Module language MUMPS</entry>
  <entry></entry>
 </row>
 <row>
  <entry>B116</entry>
  <entry></entry>
  <entry>Module language Pascal</entry>
  <entry></entry>
 </row>
 <row>
  <entry>B117</entry>
  <entry></entry>
  <entry>Module language PL/I</entry>
  <entry></entry>
 </row>
 <row>
  <entry>B121</entry>
  <entry></entry>
  <entry>Routine language Ada</entry>
  <entry></entry>
 </row>
 <row>
  <entry>B122</entry>
  <entry></entry>
  <entry>Routine language C</entry>
  <entry></entry>
 </row>
 <row>
  <entry>B123</entry>
  <entry></entry>
  <entry>Routine language COBOL</entry>
  <entry></entry>
 </row>
 <row>
  <entry>B124</entry>
  <entry></entry>
  <entry>Routine language Fortran</entry>
  <entry></entry>
 </row>
 <row>
  <entry>B125</entry>
  <entry></entry>
  <entry>Routine language MUMPS</entry>
  <entry></entry>
 </row>
 <row>
  <entry>B126</entry>
  <entry></entry>
  <entry>Routine language Pascal</entry>
  <entry></entry>
 </row>
 <row>
  <entry>B127</entry>
  <entry></entry>
  <entry>Routine language PL/I</entry>
  <entry></entry>
 </row>
 <row>
  <entry>B128</entry>
  <entry></entry>
  <entry>Routine language SQL</entry>
  <entry></entry>
 </row>
 <row>
  <entry>C011</entry>
  <entry>Core</entry>
  <entry>Call-Level Interface</entry>
  <entry></entry>
 </row>
 <row>
  <entry>E081</entry>
  <entry>Core</entry>
  <entry>Basic Privileges</entry>
  <entry></entry>
 </row>
 <row>
  <entry>E081-05</entry>
  <entry>Core</entry>
  <entry>UPDATE privilege at the column level</entry>
  <entry></entry>
 </row>
 <row>
  <entry>E081-07</entry>
  <entry>Core</entry>
  <entry>REFERENCES privilege at the column level</entry>
  <entry></entry>
 </row>
 <row>
  <entry>E081-09</entry>
  <entry>Core</entry>
  <entry>USAGE privilege</entry>
  <entry></entry>
 </row>
 <row>
  <entry>E121</entry>
  <entry>Core</entry>
  <entry>Basic cursor support</entry>
  <entry></entry>
 </row>
 <row>
  <entry>E121-06</entry>
  <entry>Core</entry>
  <entry>Positioned UPDATE statement</entry>
  <entry></entry>
 </row>
 <row>
  <entry>E121-07</entry>
  <entry>Core</entry>
  <entry>Positioned DELETE statement</entry>
  <entry></entry>
 </row>
 <row>
  <entry>E153</entry>
  <entry>Core</entry>
  <entry>Updatable queries with subqueries</entry>
  <entry></entry>
 </row>
 <row>
  <entry>E182</entry>
  <entry>Core</entry>
  <entry>Module language</entry>
  <entry></entry>
 </row>
 <row>
  <entry>F121</entry>
  <entry></entry>
  <entry>Basic diagnostics management</entry>
  <entry></entry>
 </row>
 <row>
  <entry>F121-01</entry>
  <entry></entry>
  <entry>GET DIAGNOSTICS statement</entry>
  <entry></entry>
 </row>
 <row>
  <entry>F121-02</entry>
  <entry></entry>
  <entry>SET TRANSACTION statement: DIAGNOSTICS SIZE clause</entry>
  <entry></entry>
 </row>
 <row>
  <entry>F181</entry>
  <entry>Core</entry>
  <entry>Multiple module support</entry>
  <entry></entry>
 </row>
 <row>
  <entry>F262</entry>
  <entry></entry>
  <entry>Extended CASE expression</entry>
  <entry></entry>
 </row>
 <row>
  <entry>F263</entry>
  <entry></entry>
  <entry>Comma-separated predicates in simple CASE expression</entry>
  <entry></entry>
 </row>
 <row>
  <entry>F291</entry>
  <entry></entry>
  <entry>UNIQUE predicate</entry>
  <entry></entry>
 </row>
 <row>
  <entry>F301</entry>
  <entry></entry>
  <entry>CORRESPONDING in query expressions</entry>
  <entry></entry>
 </row>
 <row>
  <entry>F311</entry>
  <entry>Core</entry>
  <entry>Schema definition statement</entry>
  <entry></entry>
 </row>
 <row>
  <entry>F311-04</entry>
  <entry>Core</entry>
  <entry>CREATE VIEW: WITH CHECK OPTION</entry>
  <entry></entry>
 </row>
 <row>
  <entry>F312</entry>
  <entry></entry>
  <entry>MERGE statement</entry>
  <entry></entry>
 </row>
 <row>
  <entry>F341</entry>
  <entry></entry>
  <entry>Usage tables</entry>
  <entry></entry>
 </row>
 <row>
  <entry>F392</entry>
  <entry></entry>
  <entry>Unicode escapes in identifiers</entry>
  <entry></entry>
 </row>
 <row>
  <entry>F393</entry>
  <entry></entry>
  <entry>Unicode escapes in literals</entry>
  <entry></entry>
 </row>
 <row>
  <entry>F402</entry>
  <entry></entry>
  <entry>Named column joins for LOBs, arrays, and multisets</entry>
  <entry></entry>
 </row>
 <row>
  <entry>F442</entry>
  <entry></entry>
  <entry>Mixed column references in set functions</entry>
  <entry></entry>
 </row>
 <row>
  <entry>F451</entry>
  <entry></entry>
  <entry>Character set definition</entry>
  <entry></entry>
 </row>
 <row>
  <entry>F461</entry>
  <entry></entry>
  <entry>Named character sets</entry>
  <entry></entry>
 </row>
 <row>
  <entry>F521</entry>
  <entry>Enhanced integrity management</entry>
  <entry>Assertions</entry>
  <entry></entry>
 </row>
 <row>
  <entry>F641</entry>
  <entry></entry>
  <entry>Row and table constructors</entry>
  <entry></entry>
 </row>
 <row>
  <entry>F661</entry>
  <entry></entry>
  <entry>Simple tables</entry>
  <entry></entry>
 </row>
 <row>
  <entry>F671</entry>
  <entry>Enhanced integrity management</entry>
  <entry>Subqueries in CHECK</entry>
  <entry>intentionally omitted</entry>
 </row>
 <row>
  <entry>F691</entry>
  <entry></entry>
  <entry>Collation and translation</entry>
  <entry></entry>
 </row>
 <row>
  <entry>F692</entry>
  <entry></entry>
  <entry>Enhanced collation support</entry>
  <entry></entry>
 </row>
 <row>
  <entry>F693</entry>
  <entry></entry>
  <entry>SQL-session and client module collations</entry>
  <entry></entry>
 </row>
 <row>
  <entry>F695</entry>
  <entry></entry>
  <entry>Translation support</entry>
  <entry></entry>
 </row>
 <row>
  <entry>F696</entry>
  <entry></entry>
  <entry>Additional translation documentation</entry>
  <entry></entry>
 </row>
 <row>
  <entry>F721</entry>
  <entry></entry>
  <entry>Deferrable constraints</entry>
  <entry>foreign keys only</entry>
 </row>
 <row>
  <entry>F731</entry>
  <entry></entry>
  <entry>INSERT column privileges</entry>
  <entry></entry>
 </row>
 <row>
  <entry>F741</entry>
  <entry></entry>
  <entry>Referential MATCH types</entry>
  <entry>no partial match yet</entry>
 </row>
 <row>
  <entry>F751</entry>
  <entry></entry>
  <entry>View CHECK enhancements</entry>
  <entry></entry>
 </row>
 <row>
  <entry>F811</entry>
  <entry></entry>
  <entry>Extended flagging</entry>
  <entry></entry>
 </row>
 <row>
  <entry>F812</entry>
  <entry>Core</entry>
  <entry>Basic flagging</entry>
  <entry></entry>
 </row>
 <row>
  <entry>F813</entry>
  <entry></entry>
  <entry>Extended flagging</entry>
  <entry></entry>
 </row>
 <row>
  <entry>F821</entry>
  <entry></entry>
  <entry>Local table references</entry>
  <entry></entry>
 </row>
 <row>
  <entry>F831</entry>
  <entry></entry>
  <entry>Full cursor update</entry>
  <entry></entry>
 </row>
 <row>
  <entry>F831-01</entry>
  <entry></entry>
  <entry>Updatable scrollable cursors</entry>
  <entry></entry>
 </row>
 <row>
  <entry>F831-02</entry>
  <entry></entry>
  <entry>Updatable ordered cursors</entry>
  <entry></entry>
 </row>
 <row>
  <entry>S011</entry>
  <entry>Core</entry>
  <entry>Distinct data types</entry>
  <entry></entry>
 </row>
 <row>
  <entry>S011-01</entry>
  <entry>Core</entry>
  <entry>USER_DEFINED_TYPES view</entry>
  <entry></entry>
 </row>
 <row>
  <entry>S023</entry>
  <entry>Basic object support</entry>
  <entry>Basic structured types</entry>
  <entry></entry>
 </row>
 <row>
  <entry>S024</entry>
  <entry>Enhanced object support</entry>
  <entry>Enhanced structured types</entry>
  <entry></entry>
 </row>
 <row>
  <entry>S025</entry>
  <entry></entry>
  <entry>Final structured types</entry>
  <entry></entry>
 </row>
 <row>
  <entry>S026</entry>
  <entry></entry>
  <entry>Self-referencing structured types</entry>
  <entry></entry>
 </row>
 <row>
  <entry>S027</entry>
  <entry></entry>
  <entry>Create method by specific method name</entry>
  <entry></entry>
 </row>
 <row>
  <entry>S028</entry>
  <entry></entry>
  <entry>Permutable UDT options list</entry>
  <entry></entry>
 </row>
 <row>
  <entry>S041</entry>
  <entry>Basic object support</entry>
  <entry>Basic reference types</entry>
  <entry></entry>
 </row>
 <row>
  <entry>S043</entry>
  <entry>Enhanced object support</entry>
  <entry>Enhanced reference types</entry>
  <entry></entry>
 </row>
 <row>
  <entry>S051</entry>
  <entry>Basic object support</entry>
  <entry>Create table of type</entry>
  <entry></entry>
 </row>
 <row>
  <entry>S081</entry>
  <entry>Enhanced object support</entry>
  <entry>Subtables</entry>
  <entry></entry>
 </row>
 <row>
  <entry>S091</entry>
  <entry></entry>
  <entry>Basic array support</entry>
  <entry></entry>
 </row>
 <row>
  <entry>S091-01</entry>
  <entry></entry>
  <entry>Arrays of built-in data types</entry>
  <entry></entry>
 </row>
 <row>
  <entry>S091-02</entry>
  <entry></entry>
  <entry>Arrays of distinct types</entry>
  <entry></entry>
 </row>
 <row>
  <entry>S091-03</entry>
  <entry></entry>
  <entry>Array expressions</entry>
  <entry></entry>
 </row>
 <row>
  <entry>S092</entry>
  <entry></entry>
  <entry>Arrays of user-defined types</entry>
  <entry></entry>
 </row>
 <row>
  <entry>S094</entry>
  <entry></entry>
  <entry>Arrays of reference types</entry>
  <entry></entry>
 </row>
 <row>
  <entry>S095</entry>
  <entry></entry>
  <entry>Array constructors by query</entry>
  <entry></entry>
 </row>
 <row>
  <entry>S096</entry>
  <entry></entry>
  <entry>Optional array bounds</entry>
  <entry></entry>
 </row>
 <row>
  <entry>S097</entry>
  <entry></entry>
  <entry>Array element assignment</entry>
  <entry></entry>
 </row>
 <row>
  <entry>S151</entry>
  <entry>Basic object support</entry>
  <entry>Type predicate</entry>
  <entry></entry>
 </row>
 <row>
  <entry>S161</entry>
  <entry>Enhanced object support</entry>
  <entry>Subtype treatment</entry>
  <entry></entry>
 </row>
 <row>
  <entry>S162</entry>
  <entry></entry>
  <entry>Subtype treatment for references</entry>
  <entry></entry>
 </row>
 <row>
  <entry>S201</entry>
  <entry></entry>
  <entry>SQL-invoked routines on arrays</entry>
  <entry></entry>
 </row>
 <row>
  <entry>S201-01</entry>
  <entry></entry>
  <entry>Array parameters</entry>
  <entry></entry>
 </row>
 <row>
  <entry>S201-02</entry>
  <entry></entry>
  <entry>Array as result type of functions</entry>
  <entry></entry>
 </row>
 <row>
  <entry>S202</entry>
  <entry></entry>
  <entry>SQL-invoked routines on multisets</entry>
  <entry></entry>
 </row>
 <row>
  <entry>S231</entry>
  <entry>Enhanced object support</entry>
  <entry>Structured type locators</entry>
  <entry></entry>
 </row>
 <row>
  <entry>S232</entry>
  <entry></entry>
  <entry>Array locators</entry>
  <entry></entry>
 </row>
 <row>
  <entry>S233</entry>
  <entry></entry>
  <entry>Multiset locators</entry>
  <entry></entry>
 </row>
 <row>
  <entry>S241</entry>
  <entry></entry>
  <entry>Transform functions</entry>
  <entry></entry>
 </row>
 <row>
  <entry>S242</entry>
  <entry></entry>
  <entry>Alter transform statement</entry>
  <entry></entry>
 </row>
 <row>
  <entry>S251</entry>
  <entry></entry>
  <entry>User-defined orderings</entry>
  <entry></entry>
 </row>
 <row>
  <entry>S261</entry>
  <entry></entry>
  <entry>Specific type method</entry>
  <entry></entry>
 </row>
 <row>
  <entry>S271</entry>
  <entry></entry>
  <entry>Basic multiset support</entry>
  <entry></entry>
 </row>
 <row>
  <entry>S272</entry>
  <entry></entry>
  <entry>Multisets of user-defined types</entry>
  <entry></entry>
 </row>
 <row>
  <entry>S274</entry>
  <entry></entry>
  <entry>Multisets of reference types</entry>
  <entry></entry>
 </row>
 <row>
  <entry>S275</entry>
  <entry></entry>
  <entry>Advanced multiset support</entry>
  <entry></entry>
 </row>
 <row>
  <entry>S281</entry>
  <entry></entry>
  <entry>Nested collection types</entry>
  <entry></entry>
 </row>
 <row>
  <entry>S291</entry>
  <entry></entry>
  <entry>Unique constraint on entire row</entry>
  <entry></entry>
 </row>
 <row>
  <entry>T011</entry>
  <entry></entry>
  <entry>Timestamp in Information Schema</entry>
  <entry></entry>
 </row>
 <row>
  <entry>T041</entry>
  <entry>Basic object support</entry>
  <entry>Basic LOB data type support</entry>
  <entry></entry>
 </row>
 <row>
  <entry>T041-01</entry>
  <entry>Basic object support</entry>
  <entry>BLOB data type</entry>
  <entry></entry>
 </row>
 <row>
  <entry>T041-02</entry>
  <entry>Basic object support</entry>
  <entry>CLOB data type</entry>
  <entry></entry>
 </row>
 <row>
  <entry>T041-03</entry>
  <entry>Basic object support</entry>
  <entry>POSITION, LENGTH, LOWER, TRIM, UPPER, and SUBSTRING functions for LOB data types</entry>
  <entry></entry>
 </row>
 <row>
  <entry>T041-04</entry>
  <entry>Basic object support</entry>
  <entry>Concatenation of LOB data types</entry>
  <entry></entry>
 </row>
 <row>
  <entry>T041-05</entry>
  <entry>Basic object support</entry>
  <entry>LOB locator: non-holdable</entry>
  <entry></entry>
 </row>
 <row>
  <entry>T042</entry>
  <entry></entry>
  <entry>Extended LOB data type support</entry>
  <entry></entry>
 </row>
 <row>
  <entry>T051</entry>
  <entry></entry>
  <entry>Row types</entry>
  <entry></entry>
 </row>
 <row>
  <entry>T052</entry>
  <entry></entry>
  <entry>MAX and MIN for row types</entry>
  <entry></entry>
 </row>
 <row>
  <entry>T053</entry>
  <entry></entry>
  <entry>Explicit aliases for all-fields reference</entry>
  <entry></entry>
 </row>
 <row>
  <entry>T061</entry>
  <entry></entry>
  <entry>UCS support</entry>
  <entry></entry>
 </row>
 <row>
  <entry>T111</entry>
  <entry></entry>
  <entry>Updatable joins, unions, and columns</entry>
  <entry></entry>
 </row>
 <row>
  <entry>T121</entry>
  <entry></entry>
  <entry>WITH (excluding RECURSIVE) in query expression</entry>
  <entry></entry>
 </row>
 <row>
  <entry>T122</entry>
  <entry></entry>
  <entry>WITH (excluding RECURSIVE) in subquery</entry>
  <entry></entry>
 </row>
 <row>
  <entry>T131</entry>
  <entry></entry>
  <entry>Recursive query</entry>
  <entry></entry>
 </row>
 <row>
  <entry>T132</entry>
  <entry></entry>
  <entry>Recursive query in subquery</entry>
  <entry></entry>
 </row>
 <row>
  <entry>T152</entry>
  <entry></entry>
  <entry>DISTINCT predicate with negation</entry>
  <entry></entry>
 </row>
 <row>
  <entry>T172</entry>
  <entry></entry>
  <entry>AS subquery clause in table definition</entry>
  <entry></entry>
 </row>
 <row>
  <entry>T173</entry>
  <entry></entry>
  <entry>Extended LIKE clause in table definition</entry>
  <entry></entry>
 </row>
 <row>
  <entry>T174</entry>
  <entry></entry>
  <entry>Identity columns</entry>
  <entry></entry>
 </row>
 <row>
  <entry>T175</entry>
  <entry></entry>
  <entry>Generated columns</entry>
  <entry></entry>
 </row>
 <row>
  <entry>T176</entry>
  <entry></entry>
  <entry>Sequence generator support</entry>
  <entry></entry>
 </row>
 <row>
  <entry>T211</entry>
  <entry>Active database, Enhanced integrity management</entry>
  <entry>Basic trigger capability</entry>
  <entry></entry>
 </row>
 <row>
  <entry>T211-05</entry>
  <entry>Active database, Enhanced integrity management</entry>
  <entry>Ability to specify a search condition that must be true before the trigger is invoked</entry>
  <entry></entry>
 </row>
 <row>
  <entry>T211-06</entry>
  <entry>Active database, Enhanced integrity management</entry>
  <entry>Support for run-time rules for the interaction of triggers and constraints</entry>
  <entry></entry>
 </row>
 <row>
  <entry>T211-08</entry>
  <entry>Active database, Enhanced integrity management</entry>
  <entry>Multiple triggers for the same event are executed in the order in which they were created in the catalog</entry>
  <entry>intentionally omitted</entry>
 </row>
 <row>
  <entry>T251</entry>
  <entry></entry>
  <entry>SET TRANSACTION statement: LOCAL option</entry>
  <entry></entry>
 </row>
 <row>
  <entry>T261</entry>
  <entry></entry>
  <entry>Chained transactions</entry>
  <entry></entry>
 </row>
 <row>
  <entry>T272</entry>
  <entry></entry>
  <entry>Enhanced savepoint management</entry>
  <entry></entry>
 </row>
 <row>
  <entry>T281</entry>
  <entry></entry>
  <entry>SELECT privilege with column granularity</entry>
  <entry></entry>
 </row>
 <row>
  <entry>T301</entry>
  <entry></entry>
  <entry>Functional dependencies</entry>
  <entry></entry>
 </row>
 <row>
  <entry>T321</entry>
  <entry>Core</entry>
  <entry>Basic SQL-invoked routines</entry>
  <entry></entry>
 </row>
 <row>
  <entry>T321-02</entry>
  <entry>Core</entry>
  <entry>User-defined stored procedures with no overloading</entry>
  <entry></entry>
 </row>
 <row>
  <entry>T321-04</entry>
  <entry>Core</entry>
  <entry>CALL statement</entry>
  <entry></entry>
 </row>
 <row>
  <entry>T321-05</entry>
  <entry>Core</entry>
  <entry>RETURN statement</entry>
  <entry></entry>
 </row>
 <row>
  <entry>T324</entry>
  <entry></entry>
  <entry>Explicit security for SQL routines</entry>
  <entry></entry>
 </row>
 <row>
  <entry>T325</entry>
  <entry></entry>
  <entry>Qualified SQL parameter references</entry>
  <entry></entry>
 </row>
 <row>
  <entry>T326</entry>
  <entry></entry>
  <entry>Table functions</entry>
  <entry></entry>
 </row>
 <row>
  <entry>T331</entry>
  <entry></entry>
  <entry>Basic roles</entry>
  <entry></entry>
 </row>
 <row>
  <entry>T332</entry>
  <entry></entry>
  <entry>Extended roles</entry>
  <entry></entry>
 </row>
 <row>
  <entry>T401</entry>
  <entry></entry>
  <entry>INSERT into a cursor</entry>
  <entry></entry>
 </row>
 <row>
  <entry>T411</entry>
  <entry></entry>
  <entry>UPDATE statement: SET ROW option</entry>
  <entry></entry>
 </row>
 <row>
  <entry>T431</entry>
  <entry>OLAP</entry>
  <entry>Extended grouping capabilities</entry>
  <entry></entry>
 </row>
 <row>
  <entry>T432</entry>
  <entry></entry>
  <entry>Nested and concatenated GROUPING SETS</entry>
  <entry></entry>
 </row>
 <row>
  <entry>T433</entry>
  <entry></entry>
  <entry>Multiargument GROUPING function</entry>
  <entry></entry>
 </row>
 <row>
  <entry>T434</entry>
  <entry></entry>
  <entry>GROUP BY DISTINCT</entry>
  <entry></entry>
 </row>
 <row>
  <entry>T471</entry>
  <entry></entry>
  <entry>Result sets return value</entry>
  <entry></entry>
 </row>
 <row>
  <entry>T491</entry>
  <entry></entry>
  <entry>LATERAL derived table</entry>
  <entry></entry>
 </row>
 <row>
  <entry>T511</entry>
  <entry></entry>
  <entry>Transaction counts</entry>
  <entry></entry>
 </row>
 <row>
  <entry>T541</entry>
  <entry></entry>
  <entry>Updatable table references</entry>
  <entry></entry>
 </row>
 <row>
  <entry>T561</entry>
  <entry></entry>
  <entry>Holdable locators</entry>
  <entry></entry>
 </row>
 <row>
  <entry>T571</entry>
  <entry></entry>
  <entry>Array-returning external SQL-invoked functions</entry>
  <entry></entry>
 </row>
 <row>
  <entry>T572</entry>
  <entry></entry>
  <entry>Multiset-returning external SQL-invoked functions</entry>
  <entry></entry>
 </row>
 <row>
  <entry>T601</entry>
  <entry></entry>
  <entry>Local cursor references</entry>
  <entry></entry>
 </row>
 <row>
  <entry>T611</entry>
  <entry>OLAP</entry>
  <entry>Elementary OLAP operations</entry>
  <entry></entry>
 </row>
 <row>
  <entry>T612</entry>
  <entry></entry>
  <entry>Advanced OLAP operations</entry>
  <entry></entry>
 </row>
 <row>
  <entry>T613</entry>
  <entry></entry>
  <entry>Sampling</entry>
  <entry></entry>
 </row>
 <row>
  <entry>T621</entry>
  <entry></entry>
  <entry>Enhanced numeric functions</entry>
  <entry></entry>
 </row>
 <row>
  <entry>T631</entry>
  <entry>Core</entry>
  <entry>IN predicate with one list element</entry>
  <entry></entry>
 </row>
 <row>
  <entry>T641</entry>
  <entry></entry>
  <entry>Multiple column assignment</entry>
  <entry></entry>
 </row>
 <row>
  <entry>T651</entry>
  <entry></entry>
  <entry>SQL-schema statements in SQL routines</entry>
  <entry></entry>
 </row>
 <row>
  <entry>T652</entry>
  <entry></entry>
  <entry>SQL-dynamic statements in SQL routines</entry>
  <entry></entry>
 </row>
 <row>
  <entry>T653</entry>
  <entry></entry>
  <entry>SQL-schema statements in external routines</entry>
  <entry></entry>
 </row>
 <row>
  <entry>T654</entry>
  <entry></entry>
  <entry>SQL-dynamic statements in external routines</entry>
  <entry></entry>
 </row>
 <row>
  <entry>T655</entry>
  <entry></entry>
  <entry>Cyclically dependent routines</entry>
  <entry></entry>
 </row>
 <row>
  <entry>X012</entry>
  <entry></entry>
  <entry>Multisets of XML type</entry>
  <entry></entry>
 </row>
 <row>
  <entry>X013</entry>
  <entry></entry>
  <entry>Distinct types of XML type</entry>
  <entry></entry>
 </row>
 <row>
  <entry>X014</entry>
  <entry></entry>
  <entry>Attributes of XML type</entry>
  <entry></entry>
 </row>
 <row>
  <entry>X015</entry>
  <entry></entry>
  <entry>Fields of XML type</entry>
  <entry></entry>
 </row>
 <row>
  <entry>X035</entry>
  <entry></entry>
  <entry>XMLAgg: ORDER BY option</entry>
  <entry></entry>
 </row>
 <row>
  <entry>X080</entry>
  <entry></entry>
  <entry>Namespaces in XML publishing</entry>
  <entry></entry>
 </row>
 <row>
  <entry>X081</entry>
  <entry></entry>
  <entry>Query-level XML namespace declarations</entry>
  <entry></entry>
 </row>
 <row>
  <entry>X082</entry>
  <entry></entry>
  <entry>XML namespace declarations in DML</entry>
  <entry></entry>
 </row>
 <row>
  <entry>X083</entry>
  <entry></entry>
  <entry>XML namespace declarations in DDL</entry>
  <entry></entry>
 </row>
 <row>
  <entry>X084</entry>
  <entry></entry>
  <entry>XML namespace declarations in compound statements</entry>
  <entry></entry>
 </row>
 <row>
  <entry>X100</entry>
  <entry></entry>
  <entry>Host language support for XML: CONTENT option</entry>
  <entry></entry>
 </row>
 <row>
  <entry>X101</entry>
  <entry></entry>
  <entry>Host language support for XML: DOCUMENT option</entry>
  <entry></entry>
 </row>
 <row>
  <entry>X110</entry>
  <entry></entry>
  <entry>Host language support for XML: VARCHAR mapping</entry>
  <entry></entry>
 </row>
 <row>
  <entry>X111</entry>
  <entry></entry>
  <entry>Host language support for XML: CLOB mapping</entry>
  <entry></entry>
 </row>
 <row>
  <entry>X131</entry>
  <entry></entry>
  <entry>Query-level XMLBINARY clause</entry>
  <entry></entry>
 </row>
 <row>
  <entry>X132</entry>
  <entry></entry>
  <entry>XMLBINARY clause in DML</entry>
  <entry></entry>
 </row>
 <row>
  <entry>X133</entry>
  <entry></entry>
  <entry>XMLBINARY clause in DDL</entry>
  <entry></entry>
 </row>
 <row>
  <entry>X134</entry>
  <entry></entry>
  <entry>XMLBINARY clause in compound statements</entry>
  <entry></entry>
 </row>
 <row>
  <entry>X135</entry>
  <entry></entry>
  <entry>XMLBINARY clause in subqueries</entry>
  <entry></entry>
 </row>
</tbody>
